{
  "main": {
    "id": "dd31342dd635dc8b",
    "type": "split",
    "children": [
      {
        "id": "8190f5a1c623f53d",
        "type": "tabs",
        "children": [
          {
            "id": "11fd2dcc67cddbf2",
            "type": "leaf",
            "state": {
              "type": "markdown",
              "state": {
                "file": "Languages/Java/Java.md",
                "mode": "source",
                "source": false
              },
              "icon": "lucide-file",
              "title": "Java"
            }
          }
        ]
      }
    ],
    "direction": "vertical"
  },
  "left": {
    "id": "036f28d3efb367fc",
    "type": "split",
    "children": [
      {
        "id": "3adab63b3ad090d7",
        "type": "tabs",
        "children": [
          {
            "id": "9d090446acb8ba33",
            "type": "leaf",
            "state": {
              "type": "file-explorer",
              "state": {
                "sortOrder": "alphabetical",
                "autoReveal": false
              },
              "icon": "lucide-folder-closed",
              "title": "Files"
            }
          },
          {
            "id": "95b85bee44a85cfb",
            "type": "leaf",
            "state": {
              "type": "search",
              "state": {
                "query": "",
                "matchingCase": false,
                "explainSearch": false,
                "collapseAll": false,
                "extraContext": false,
                "sortOrder": "alphabetical"
              },
              "icon": "lucide-search",
              "title": "Search"
            }
          },
          {
            "id": "9ec3ba54aa314c84",
            "type": "leaf",
            "state": {
              "type": "bookmarks",
              "state": {},
              "icon": "lucide-bookmark",
              "title": "Bookmarks"
            }
          }
        ]
      }
    ],
    "direction": "horizontal",
    "width": 300
  },
  "right": {
    "id": "0710fbdc27d10fe7",
    "type": "split",
    "children": [
      {
        "id": "22c821c9e2f6c3bc",
        "type": "tabs",
        "children": [
          {
            "id": "8a750fb05ce7436d",
            "type": "leaf",
            "state": {
              "type": "backlink",
              "state": {
                "file": "learning python.md",
                "collapseAll": false,
                "extraContext": false,
                "sortOrder": "alphabetical",
                "showSearch": false,
                "searchQuery": "",
                "backlinkCollapsed": false,
                "unlinkedCollapsed": true
              },
              "icon": "links-coming-in",
              "title": "Backlinks for learning python"
            }
          },
          {
            "id": "bb26117ac27ff9d0",
            "type": "leaf",
            "state": {
              "type": "outgoing-link",
              "state": {
                "file": "learning python.md",
                "linksCollapsed": false,
                "unlinkedCollapsed": true
              },
              "icon": "links-going-out",
              "title": "Outgoing links from learning python"
            }
          },
          {
            "id": "3b69aa3a15483f3c",
            "type": "leaf",
            "state": {
              "type": "tag",
              "state": {
                "sortOrder": "frequency",
                "useHierarchy": true,
                "showSearch": false,
                "searchQuery": ""
              },
              "icon": "lucide-tags",
              "title": "Tags"
            }
          },
          {
            "id": "88d82dd4535aca3f",
            "type": "leaf",
            "state": {
              "type": "outline",
              "state": {
                "file": "learning python.md",
                "followCursor": false,
                "showSearch": false,
                "searchQuery": ""
              },
              "icon": "lucide-list",
              "title": "Outline of learning python"
            }
          }
        ]
      }
    ],
    "direction": "horizontal",
    "width": 300,
    "collapsed": true
  },
  "left-ribbon": {
    "hiddenItems": {
      "switcher:Open quick switcher": false,
      "graph:Open graph view": false,
      "canvas:Create new canvas": false,
      "daily-notes:Open today's daily note": false,
      "templates:Insert template": false,
      "command-palette:Open command palette": false
    }
  },
  "active": "11fd2dcc67cddbf2",
  "lastOpenFiles": [
    "Languages/Python.md",
    "Languages/Java/Java.md",
    "Languages/Java",
    "Languages/C++/1-CPP.md",
    "Languages/C++/variables with different modifiers.md",
    "top_250_anime_checklist.md",
    "Languages/C++",
    "Languages",
    "learning python.md",
    "Welcome.md",
    "top_100_must_watch_anime.md"
  ]
}